eta_components/__init__.py
eta_components/milp_component_library/__init__.py
eta_components/milp_component_library/base_object.py
eta_components/milp_component_library/base_object_copy.py
eta_components/milp_component_library/custom_types.py
eta_components/milp_component_library/environments.py
eta_components/milp_component_library/exceptions.py
eta_components/milp_component_library/networks.py
eta_components/milp_component_library/objectives.py
eta_components/milp_component_library/systems.py
eta_components/milp_component_library/units/__init__.py
eta_components/milp_component_library/units/base_unit.py
eta_components/milp_component_library/units/equipment/__init__.py
eta_components/milp_component_library/units/equipment/base_equipment.py
eta_components/milp_component_library/units/equipment/dimensioning/__init__.py
eta_components/milp_component_library/units/equipment/dimensioning/base_dimensioning.py
eta_components/milp_component_library/units/equipment/dimensioning/heat_exchanger.py
eta_components/milp_component_library/units/equipment/dimensioning/heat_pump.py
eta_components/milp_component_library/units/equipment/dimensioning/storage.py
eta_components/milp_component_library/units/equipment/operational/__init__.py
eta_components/milp_component_library/units/equipment/operational/absorption_chiller.py
eta_components/milp_component_library/units/equipment/operational/base_operational.py
eta_components/milp_component_library/units/equipment/operational/boiler.py
eta_components/milp_component_library/units/equipment/operational/chp.py
eta_components/milp_component_library/units/equipment/operational/compression_chiller.py
eta_components/milp_component_library/units/equipment/operational/free_cooler.py
eta_components/milp_component_library/units/equipment/operational/heat_exchanger.py
eta_components/milp_component_library/units/equipment/operational/heat_pump.py
eta_components/milp_component_library/units/equipment/operational/inverter.py
eta_components-0.0.5.dist-info/LICENSE
eta_components-0.0.5.dist-info/METADATA
eta_components-0.0.5.dist-info/WHEEL
eta_components-0.0.5.dist-info/RECORD
