Metadata-Version: 2.3
Name: eta-components
Version: 0.0.5
Summary: Components for modeling industrial production sites
License: BSD-2-Clause License
Keywords: modeling,milp,library
Author: Technical University of Darmstadt, Institute for Production Management, Technology and Machine Tools (PTW)
Author-email: m.frank@ptw.tu-darmstadt.de
Requires-Python: >=3.11, <3.14
Classifier: Development Status :: 4 - Beta
Classifier: Intended Audience :: Developers
Classifier: Intended Audience :: Manufacturing
Classifier: Intended Audience :: Science/Research
Classifier: License :: OSI Approved :: BSD License
Classifier: License :: Other/Proprietary License
Classifier: Operating System :: OS Independent
Classifier: Programming Language :: Python :: 3
Classifier: Programming Language :: Python :: 3.11
Classifier: Programming Language :: Python :: 3.12
Classifier: Programming Language :: Python :: 3.13
Classifier: Topic :: Scientific/Engineering :: Artificial Intelligence
Requires-Dist: pydantic (>=2.11.7,<3.0.0)
Requires-Dist: pyomo (>=6.9.2,<7.0.0)
Requires-Dist: pytest (>=8.3.5,<9.0.0)
Requires-Dist: pytest-cov (>=6.1.1,<7.0.0)
Requires-Dist: snakeviz (>=2.2.2,<3.0.0)
Requires-Dist: stable_baselines3 (>=2.1,<3.0)
Requires-Dist: tabulate (>=0.9.0,<0.10.0)
Requires-Dist: tsam (>=2.3.7,<3.0.0)
Project-URL: Homepage, https://www.ptw.tu-darmstadt.de
